aiohttp_utils/__init__.py
aiohttp_utils/constants.py
aiohttp_utils/negotiation.py
aiohttp_utils/routing.py
aiohttp_utils/runner.py
aiohttp_utils-3.2.1.dist-info/LICENSE
aiohttp_utils-3.2.1.dist-info/METADATA
aiohttp_utils-3.2.1.dist-info/WHEEL
aiohttp_utils-3.2.1.dist-info/top_level.txt
aiohttp_utils-3.2.1.dist-info/RECORD
