Metadata-Version: 2.1
Name: aiohttp-utils
Version: 3.2.1
Summary: Handy utilities for aiohttp.web applications.
Home-page: https://github.com/sloria/aiohttp-utils
Author: Steven Loria
Author-email: sloria1@gmail.com
License: MIT
Keywords: aiohttp_utils aiohttp utilities aiohttp.web
Classifier: Development Status :: 2 - Pre-Alpha
Classifier: Intended Audience :: Developers
Classifier: License :: OSI Approved :: MIT License
Classifier: Natural Language :: English
Classifier: Programming Language :: Python :: 3
Classifier: Programming Language :: Python :: 3.5
Classifier: Programming Language :: Python :: 3.6
Classifier: Programming Language :: Python :: 3.7
License-File: LICENSE
Requires-Dist: aiohttp (>=3)
Requires-Dist: python-mimeparse
Requires-Dist: gunicorn
